Orange3_WFDB-0.0.2-py3.12-nspkg.pth
orangecontrib/wfdb/__init__.py
orangecontrib/wfdb/io/__init__.py
orangecontrib/wfdb/io/wfdb.py
orangecontrib/wfdb/widgets/__init__.py
orangecontrib/wfdb/widgets/owcleanwfdbsignal.py
orangecontrib/wfdb/widgets/owwfdbdatasets.py
orangecontrib/wfdb/widgets/icons/Category-WFDB.svg
orangecontrib/wfdb/widgets/icons/clean_wfdb.svg
Orange3_WFDB-0.0.2.dist-info/LICENSE
Orange3_WFDB-0.0.2.dist-info/METADATA
Orange3_WFDB-0.0.2.dist-info/WHEEL
Orange3_WFDB-0.0.2.dist-info/entry_points.txt
Orange3_WFDB-0.0.2.dist-info/namespace_packages.txt
Orange3_WFDB-0.0.2.dist-info/top_level.txt
Orange3_WFDB-0.0.2.dist-info/RECORD
