Metadata-Version: 2.1
Name: Orange3-WFDB
Version: 0.0.2
Summary: Orange3 add-on for PhysioNet's Waveform Database data mining.
Home-page: https://github.com/chrislee35/orange3-wfdb
Author: Chris Lee
Author-email: github@chrislee.dhs.org
License: GPL3+
Keywords: orange3 add-on,orange3-wfdb
Classifier: Development Status :: 1 - Planning
Classifier: Intended Audience :: Education
Classifier: Intended Audience :: Science/Research
Classifier: License :: OSI Approved :: GNU General Public License v3 or later (GPLv3+)
Classifier: Programming Language :: Python :: 3 :: Only
License-File: LICENSE
Requires-Dist: AnyQt
Requires-Dist: ndf >=0.1.4
Requires-Dist: numpy >=1.16
Requires-Dist: Orange3 >=3.34.0
Requires-Dist: orange-canvas-core >=0.1.28
Requires-Dist: orange-widget-base >=4.20.0
Requires-Dist: pandas <2.1
Requires-Dist: wfdb >=4.1.2
Requires-Dist: requests
Requires-Dist: requests-cache
Requires-Dist: scipy
Provides-Extra: doc
Requires-Dist: sphinx ; extra == 'doc'
Requires-Dist: recommonmark ; extra == 'doc'
Requires-Dist: sphinx-rtd-theme ; extra == 'doc'
Provides-Extra: test
Requires-Dist: coverage ; extra == 'test'
